pymysq1/__init__.py
pymysq1/connection.py
pymysq1/setings.py
pymysq1_connect-0.0.1.dist-info/METADATA
pymysq1_connect-0.0.1.dist-info/WHEEL
pymysq1_connect-0.0.1.dist-info/top_level.txt
pymysq1_connect-0.0.1.dist-info/RECORD
