Metadata-Version: 2.1
Name: pymysq1-connect
Version: 0.0.1
Summary: This is the simplest module for connect to mysql
Home-page: https://github.com/artur4real/Triangle
Author: PythonIntepritator
Author-email: Python@gmail.com
Project-URL: GitHub, https://github.com/artur4real/Triangle
Keywords: files speedfiles
Classifier: Programming Language :: Python :: 3.11
Classifier: License :: OSI Approved :: MIT License
Classifier: Operating System :: OS Independent
Requires-Python: >=3.6
Requires-Dist: requests >=2.25.1
